rankor/__init__.py
rankor/contrasts.py
rankor/imputation.py
rankor/quantification.py
rankor/rankor.py
rankor/reducer.py
rankor-0.2.0.dist-info/LICENSE
rankor-0.2.0.dist-info/METADATA
rankor-0.2.0.dist-info/WHEEL
rankor-0.2.0.dist-info/top_level.txt
rankor-0.2.0.dist-info/RECORD
