Metadata-Version: 2.1
Name: rankor
Version: 0.2.0
Summary: Rankor Analysis
Home-page: https://github.com/richardtjornhammar/rankor
Author: Richard Tjörnhammar
Author-email: richard.tjornhammar@gmail.com
License: UNKNOWN
Platform: UNKNOWN
Classifier: Programming Language :: Python :: 3
Classifier: License :: OSI Approved :: Apache Software License
Classifier: Operating System :: OS Independent
